<chunk name="Object" index="0">
  <items count="2">
    <item name="GUID" type_name="gh_guid" type_code="9">b6236720-8d88-4289-93c3-ac4c99f9b97b</item>
    <item name="Name" type_name="gh_string" type_code="10">Relay</item>
  </items>
  <chunks count="1">
    <chunk name="Container">
      <items count="8">
        <item name="Access" type_name="gh_int32" type_code="3">2</item>
        <item name="Description" type_name="gh_string" type_code="10">A wire relay object</item>
        <item name="InstanceGuid" type_name="gh_guid" type_code="9">5907db94-59ab-435e-ac7a-f96a6f3c3ae4</item>
        <item name="Name" type_name="gh_string" type_code="10">Relay</item>
        <item name="NickName" type_name="gh_string" type_code="10">RS2 +90</item>
        <item name="Optional" type_name="gh_bool" type_code="1">false</item>
        <item name="Source" index="0" type_name="gh_guid" type_code="9">f2c95bd9-f1fe-491d-b940-c52d3934ca4c</item>
        <item name="SourceCount" type_name="gh_int32" type_code="3">1</item>
      </items>
      <chunks count="1">
        <chunk name="Attributes">
          <items count="2">
            <item name="Bounds" type_name="gh_drawing_rectanglef" type_code="35">
              <X>35808</X>
              <Y>11005</Y>
              <W>62</W>
              <H>16</H>
            </item>
            <item name="Pivot" type_name="gh_drawing_pointf" type_code="31">
              <X>35839</X>
              <Y>11013</Y>
            </item>
          </items>
        </chunk>
      </chunks>
    </chunk>
  </chunks>
</chunk>