<chunk name="Object" index="0">
  <items count="2">
    <item name="GUID" type_name="gh_guid" type_code="9">3581f42a-9592-4549-bd6b-1c0fc39d067b</item>
    <item name="Name" type_name="gh_string" type_code="10">Construct Point</item>
  </items>
  <chunks count="1">
    <chunk name="Container">
      <items count="5">
        <item name="Description" type_name="gh_string" type_code="10">Construct a point from {xyz} coordinates.</item>
        <item name="Hidden" type_name="gh_bool" type_code="1">true</item>
        <item name="InstanceGuid" type_name="gh_guid" type_code="9">6770be8e-77cf-4dda-83f7-0f13dcb714c6</item>
        <item name="Name" type_name="gh_string" type_code="10">Construct Point</item>
        <item name="NickName" type_name="gh_string" type_code="10">Pt</item>
      </items>
      <chunks count="5">
        <chunk name="Attributes">
          <items count="2">
            <item name="Bounds" type_name="gh_drawing_rectanglef" type_code="35">
              <X>-119</X>
              <Y>9375</Y>
              <W>68</W>
              <H>64</H>
            </item>
            <item name="Pivot" type_name="gh_drawing_pointf" type_code="31">
              <X>-88</X>
              <Y>9407</Y>
            </item>
          </items>
        </chunk>
        <chunk name="param_input" index="0">
          <items count="7">
            <item name="Description" type_name="gh_string" type_code="10">{x} coordinate</item>
            <item name="InstanceGuid" type_name="gh_guid" type_code="9">6ba1bcd3-d343-4e16-8d53-3e1a8bc9f029</item>
            <item name="Name" type_name="gh_string" type_code="10">X coordinate</item>
            <item name="NickName" type_name="gh_string" type_code="10">X</item>
            <item name="Optional" type_name="gh_bool" type_code="1">false</item>
            <item name="Source" index="0" type_name="gh_guid" type_code="9">5aef2d0f-19a6-4e47-85ae-6a67fe7364ce</item>
            <item name="SourceCount" type_name="gh_int32" type_code="3">1</item>
          </items>
          <chunks count="2">
            <chunk name="Attributes">
              <items count="2">
                <item name="Bounds" type_name="gh_drawing_rectanglef" type_code="35">
                  <X>-117</X>
                  <Y>9377</Y>
                  <W>14</W>
                  <H>20</H>
                </item>
                <item name="Pivot" type_name="gh_drawing_pointf" type_code="31">
                  <X>-108.5</X>
                  <Y>9387</Y>
                </item>
              </items>
            </chunk>
            <chunk name="PersistentData">
              <items count="1">
                <item name="Count" type_name="gh_int32" type_code="3">1</item>
              </items>
              <chunks count="1">
                <chunk name="Branch" index="0">
                  <items count="2">
                    <item name="Count" type_name="gh_int32" type_code="3">1</item>
                    <item name="Path" type_name="gh_string" type_code="10">{0}</item>
                  </items>
                  <chunks count="1">
                    <chunk name="Item" index="0">
                      <items count="1">
                        <item name="number" type_name="gh_double" type_code="6">0</item>
                      </items>
                    </chunk>
                  </chunks>
                </chunk>
              </chunks>
            </chunk>
          </chunks>
        </chunk>
        <chunk name="param_input" index="1">
          <items count="6">
            <item name="Description" type_name="gh_string" type_code="10">{y} coordinate</item>
            <item name="InstanceGuid" type_name="gh_guid" type_code="9">9aff43a6-5dfe-4cb9-997d-61a7a67cbfe4</item>
            <item name="Name" type_name="gh_string" type_code="10">Y coordinate</item>
            <item name="NickName" type_name="gh_string" type_code="10">Y</item>
            <item name="Optional" type_name="gh_bool" type_code="1">false</item>
            <item name="SourceCount" type_name="gh_int32" type_code="3">0</item>
          </items>
          <chunks count="2">
            <chunk name="Attributes">
              <items count="2">
                <item name="Bounds" type_name="gh_drawing_rectanglef" type_code="35">
                  <X>-117</X>
                  <Y>9397</Y>
                  <W>14</W>
                  <H>20</H>
                </item>
                <item name="Pivot" type_name="gh_drawing_pointf" type_code="31">
                  <X>-108.5</X>
                  <Y>9407</Y>
                </item>
              </items>
            </chunk>
            <chunk name="PersistentData">
              <items count="1">
                <item name="Count" type_name="gh_int32" type_code="3">1</item>
              </items>
              <chunks count="1">
                <chunk name="Branch" index="0">
                  <items count="2">
                    <item name="Count" type_name="gh_int32" type_code="3">1</item>
                    <item name="Path" type_name="gh_string" type_code="10">{0}</item>
                  </items>
                  <chunks count="1">
                    <chunk name="Item" index="0">
                      <items count="1">
                        <item name="number" type_name="gh_double" type_code="6">0</item>
                      </items>
                    </chunk>
                  </chunks>
                </chunk>
              </chunks>
            </chunk>
          </chunks>
        </chunk>
        <chunk name="param_input" index="2">
          <items count="7">
            <item name="Description" type_name="gh_string" type_code="10">{z} coordinate</item>
            <item name="InstanceGuid" type_name="gh_guid" type_code="9">ca207b45-eca1-4f9f-894d-129d7b6746b3</item>
            <item name="Name" type_name="gh_string" type_code="10">Z coordinate</item>
            <item name="NickName" type_name="gh_string" type_code="10">Z</item>
            <item name="Optional" type_name="gh_bool" type_code="1">false</item>
            <item name="Source" index="0" type_name="gh_guid" type_code="9">7ed54cb2-2aa7-4091-9809-1744d36df122</item>
            <item name="SourceCount" type_name="gh_int32" type_code="3">1</item>
          </items>
          <chunks count="2">
            <chunk name="Attributes">
              <items count="2">
                <item name="Bounds" type_name="gh_drawing_rectanglef" type_code="35">
                  <X>-117</X>
                  <Y>9417</Y>
                  <W>14</W>
                  <H>20</H>
                </item>
                <item name="Pivot" type_name="gh_drawing_pointf" type_code="31">
                  <X>-108.5</X>
                  <Y>9427</Y>
                </item>
              </items>
            </chunk>
            <chunk name="PersistentData">
              <items count="1">
                <item name="Count" type_name="gh_int32" type_code="3">1</item>
              </items>
              <chunks count="1">
                <chunk name="Branch" index="0">
                  <items count="2">
                    <item name="Count" type_name="gh_int32" type_code="3">1</item>
                    <item name="Path" type_name="gh_string" type_code="10">{0}</item>
                  </items>
                  <chunks count="1">
                    <chunk name="Item" index="0">
                      <items count="1">
                        <item name="number" type_name="gh_double" type_code="6">0</item>
                      </items>
                    </chunk>
                  </chunks>
                </chunk>
              </chunks>
            </chunk>
          </chunks>
        </chunk>
        <chunk name="param_output" index="0">
          <items count="6">
            <item name="Description" type_name="gh_string" type_code="10">Point coordinate</item>
            <item name="InstanceGuid" type_name="gh_guid" type_code="9">5a658caf-7062-4963-8cc4-012f8615efcc</item>
            <item name="Name" type_name="gh_string" type_code="10">Point</item>
            <item name="NickName" type_name="gh_string" type_code="10">Pt</item>
            <item name="Optional" type_name="gh_bool" type_code="1">false</item>
            <item name="SourceCount" type_name="gh_int32" type_code="3">0</item>
          </items>
          <chunks count="1">
            <chunk name="Attributes">
              <items count="2">
                <item name="Bounds" type_name="gh_drawing_rectanglef" type_code="35">
                  <X>-73</X>
                  <Y>9377</Y>
                  <W>20</W>
                  <H>60</H>
                </item>
                <item name="Pivot" type_name="gh_drawing_pointf" type_code="31">
                  <X>-63</X>
                  <Y>9407</Y>
                </item>
              </items>
            </chunk>
          </chunks>
        </chunk>
      </chunks>
    </chunk>
  </chunks>
</chunk>